cataclysm/__init__.py
cataclysm/__main__.py
cataclysm/default_files/datafiles/plunkylib/params/CataclysmLLMParams.yml
cataclysm/default_files/datafiles/plunkylib/params/CataclysmLLMParams_3-5.yml
cataclysm/default_files/datafiles/plunkylib/petition/CataclysmQuery.yml
cataclysm/default_files/datafiles/plunkylib/prompts/CataclysmPrompt.yml
cataclysm/default_files/env.template.cataclysm
cataclysm/doomed.py
cataclysm/total/__init__.py
cataclysm/yamlformat.py
cataclysm-0.1.2.dist-info/entry_points.txt
cataclysm-0.1.2.dist-info/LICENSE
cataclysm-0.1.2.dist-info/METADATA
cataclysm-0.1.2.dist-info/WHEEL
cataclysm-0.1.2.dist-info/RECORD
