Metadata-Version: 2.1
Name: cataclysm
Version: 0.1.2
Summary: The Last Library
License: MIT
Author: Mattie Casper
Requires-Python: >=3.10,<4.0
Classifier: License :: OSI Approved :: MIT License
Classifier: Programming Language :: Python :: 3
Classifier: Programming Language :: Python :: 3.10
Classifier: Programming Language :: Python :: 3.11
Requires-Dist: datafiles (>=2.1,<3.0)
Requires-Dist: loguru (>=0.6.0,<0.7.0)
Requires-Dist: openai (>=0.27.2,<0.28.0)
Requires-Dist: plunkylib (>=0.1.4,<0.2.0)
